{
	"$schema": "http://schema.management.azure.com/schemas/2015-01-01/deploymentTemplate.json#",
	"contentVersion": "1.0.0.0",
	"parameters": {
		"factoryName": {
			"type": "string",
			"metadata": "Data Factory name",
			"defaultValue": "DF-ADENOV24"
		},
		"LS_ADLS_KV_properties_typeProperties_url": {
			"type": "string",
			"defaultValue": "https://adlsnov24.dfs.core.windows.net/"
		},
		"LS_DBS_properties_typeProperties_existingClusterId": {
			"type": "string",
			"defaultValue": "1125-042634-k34o40e7"
		},
		"LS_SQL2_properties_typeProperties_server": {
			"type": "string",
			"defaultValue": "sqlservernov24.database.windows.net"
		},
		"LS_SQL2_properties_typeProperties_database": {
			"type": "string",
			"defaultValue": "dbadenov24"
		},
		"LS_SQL2_properties_typeProperties_userName": {
			"type": "string",
			"defaultValue": "sqladmin"
		}
	},
	"variables": {
		"factoryId": "[concat('Microsoft.DataFactory/factories/', parameters('factoryName'))]"
	},
	"resources": [
		{
			"name": "[concat(parameters('factoryName'), '/LS_ADLS_KV')]",
			"type": "Microsoft.DataFactory/factories/linkedServices",
			"apiVersion": "2018-06-01",
			"properties": {
				"annotations": [],
				"type": "AzureBlobFS",
				"typeProperties": {
					"url": "[parameters('LS_ADLS_KV_properties_typeProperties_url')]",
					"accountKey": {
						"type": "AzureKeyVaultSecret",
						"store": {
							"referenceName": "LS_KV",
							"type": "LinkedServiceReference"
						},
						"secretName": "adlskey"
					}
				}
			},
			"dependsOn": []
		},
		{
			"name": "[concat(parameters('factoryName'), '/LS_DBS')]",
			"type": "Microsoft.DataFactory/factories/linkedServices",
			"apiVersion": "2018-06-01",
			"properties": {
				"annotations": [],
				"type": "AzureDatabricks",
				"typeProperties": {
					"domain": "https://adb-2113887825683399.19.azuredatabricks.net",
					"accessToken": {
						"type": "AzureKeyVaultSecret",
						"store": {
							"referenceName": "LS_KV",
							"type": "LinkedServiceReference"
						},
						"secretName": "accesstoken"
					},
					"existingClusterId": "[parameters('LS_DBS_properties_typeProperties_existingClusterId')]"
				}
			},
			"dependsOn": []
		},
		{
			"name": "[concat(parameters('factoryName'), '/LS_SQL2')]",
			"type": "Microsoft.DataFactory/factories/linkedServices",
			"apiVersion": "2018-06-01",
			"properties": {
				"annotations": [],
				"type": "AzureSqlDatabase",
				"typeProperties": {
					"server": "[parameters('LS_SQL2_properties_typeProperties_server')]",
					"database": "[parameters('LS_SQL2_properties_typeProperties_database')]",
					"encrypt": "mandatory",
					"trustServerCertificate": false,
					"authenticationType": "SQL",
					"userName": "[parameters('LS_SQL2_properties_typeProperties_userName')]",
					"password": {
						"type": "AzureKeyVaultSecret",
						"store": {
							"referenceName": "LS_KV",
							"type": "LinkedServiceReference"
						},
						"secretName": "sqlpassword"
					}
				}
			},
			"dependsOn": []
		},
		{
			"name": "[concat(parameters('factoryName'), '/DAILY 9 AM')]",
			"type": "Microsoft.DataFactory/factories/triggers",
			"apiVersion": "2018-06-01",
			"properties": {
				"annotations": [],
				"runtimeState": "Stopped",
				"pipelines": [
					{
						"pipelineReference": {
							"referenceName": "Schedule_Trigger",
							"type": "PipelineReference"
						},
						"parameters": {}
					},
					{
						"pipelineReference": {
							"referenceName": "Schedule_PIPELINE2",
							"type": "PipelineReference"
						},
						"parameters": {}
					}
				],
				"type": "ScheduleTrigger",
				"typeProperties": {
					"recurrence": {
						"frequency": "Day",
						"interval": 1,
						"startTime": "2024-11-23T03:19:00",
						"timeZone": "India Standard Time",
						"schedule": {
							"minutes": [
								51
							],
							"hours": [
								8
							]
						}
					}
				}
			},
			"dependsOn": []
		},
		{
			"name": "[concat(parameters('factoryName'), '/Daily_6AM')]",
			"type": "Microsoft.DataFactory/factories/triggers",
			"apiVersion": "2018-06-01",
			"properties": {
				"annotations": [],
				"runtimeState": "Stopped",
				"pipelines": [
					{
						"pipelineReference": {
							"referenceName": "Schedule_Trigger",
							"type": "PipelineReference"
						},
						"parameters": {}
					}
				],
				"type": "ScheduleTrigger",
				"typeProperties": {
					"recurrence": {
						"frequency": "Day",
						"interval": 1,
						"startTime": "2024-11-22T08:45:00",
						"timeZone": "India Standard Time",
						"schedule": {
							"minutes": [
								50
							],
							"hours": [
								8
							]
						}
					}
				}
			},
			"dependsOn": []
		},
		{
			"name": "[concat(parameters('factoryName'), '/BRONZE_2_SILVER')]",
			"type": "Microsoft.DataFactory/factories/pipelines",
			"apiVersion": "2018-06-01",
			"properties": {
				"activities": [
					{
						"name": "Notebook1",
						"type": "DatabricksNotebook",
						"dependsOn": [],
						"policy": {
							"timeout": "0.12:00:00",
							"retry": 0,
							"retryIntervalInSeconds": 30,
							"secureOutput": false,
							"secureInput": false
						},
						"userProperties": [],
						"typeProperties": {
							"notebookPath": "/Users/bollachanti@gmail.com/Bronze_2_Silver"
						},
						"linkedServiceName": {
							"referenceName": "LS_DBS",
							"type": "LinkedServiceReference"
						}
					}
				],
				"policy": {
					"elapsedTimeMetric": {}
				},
				"annotations": [],
				"lastPublishTime": "2024-11-25T05:21:23Z"
			},
			"dependsOn": [
				"[concat(variables('factoryId'), '/linkedServices/LS_DBS')]"
			]
		},
		{
			"name": "[concat(parameters('factoryName'), '/Copy_csv_2_parquet')]",
			"type": "Microsoft.DataFactory/factories/pipelines",
			"apiVersion": "2018-06-01",
			"properties": {
				"activities": [
					{
						"name": "Copy data1",
						"type": "Copy",
						"dependsOn": [],
						"policy": {
							"timeout": "0.12:00:00",
							"retry": 0,
							"retryIntervalInSeconds": 30,
							"secureOutput": false,
							"secureInput": false
						},
						"userProperties": [],
						"typeProperties": {
							"source": {
								"type": "DelimitedTextSource",
								"storeSettings": {
									"type": "AzureBlobFSReadSettings",
									"recursive": true,
									"modifiedDatetimeStart": null,
									"modifiedDatetimeEnd": null,
									"enablePartitionDiscovery": false
								},
								"formatSettings": {
									"type": "DelimitedTextReadSettings"
								}
							},
							"sink": {
								"type": "ParquetSink",
								"storeSettings": {
									"type": "AzureBlobFSWriteSettings"
								},
								"formatSettings": {
									"type": "ParquetWriteSettings"
								}
							},
							"enableStaging": false,
							"translator": {
								"type": "TabularTranslator",
								"typeConversion": true,
								"typeConversionSettings": {
									"allowDataTruncation": true,
									"treatBooleanAsNumber": false
								}
							}
						},
						"inputs": [
							{
								"referenceName": "blob_file_param",
								"type": "DatasetReference",
								"parameters": {
									"filename": "emp_sal.csv"
								}
							}
						],
						"outputs": [
							{
								"referenceName": "Parquet_output",
								"type": "DatasetReference",
								"parameters": {}
							}
						]
					}
				],
				"policy": {
					"elapsedTimeMetric": {}
				},
				"annotations": [],
				"lastPublishTime": "2024-11-15T03:27:08Z"
			},
			"dependsOn": []
		},
		{
			"name": "[concat(parameters('factoryName'), '/DELETE_FILE')]",
			"type": "Microsoft.DataFactory/factories/pipelines",
			"apiVersion": "2018-06-01",
			"properties": {
				"activities": [
					{
						"name": "Delete1",
						"type": "Delete",
						"dependsOn": [],
						"policy": {
							"timeout": "0.12:00:00",
							"retry": 0,
							"retryIntervalInSeconds": 30,
							"secureOutput": false,
							"secureInput": false
						},
						"userProperties": [],
						"typeProperties": {
							"dataset": {
								"referenceName": "deleteactivityfolder",
								"type": "DatasetReference",
								"parameters": {}
							},
							"enableLogging": false,
							"storeSettings": {
								"type": "AzureBlobFSReadSettings",
								"recursive": true,
								"wildcardFileName": "*.csv",
								"enablePartitionDiscovery": false
							}
						}
					}
				],
				"policy": {
					"elapsedTimeMetric": {}
				},
				"annotations": [],
				"lastPublishTime": "2024-11-19T03:05:53Z"
			},
			"dependsOn": []
		},
		{
			"name": "[concat(parameters('factoryName'), '/Get_Meta')]",
			"type": "Microsoft.DataFactory/factories/pipelines",
			"apiVersion": "2018-06-01",
			"properties": {
				"activities": [
					{
						"name": "Get Metadata_FILE",
						"type": "GetMetadata",
						"dependsOn": [],
						"policy": {
							"timeout": "0.12:00:00",
							"retry": 0,
							"retryIntervalInSeconds": 30,
							"secureOutput": false,
							"secureInput": false
						},
						"userProperties": [],
						"typeProperties": {
							"dataset": {
								"referenceName": "Cus1_csv",
								"type": "DatasetReference",
								"parameters": {}
							},
							"fieldList": [
								"structure",
								"size",
								"lastModified",
								"itemType",
								"itemName",
								"exists",
								"contentMD5",
								"columnCount"
							],
							"storeSettings": {
								"type": "AzureBlobFSReadSettings",
								"recursive": true,
								"enablePartitionDiscovery": false
							},
							"formatSettings": {
								"type": "DelimitedTextReadSettings"
							}
						}
					},
					{
						"name": "Get Metadata_FOLDER",
						"type": "GetMetadata",
						"dependsOn": [],
						"policy": {
							"timeout": "0.12:00:00",
							"retry": 0,
							"retryIntervalInSeconds": 30,
							"secureOutput": false,
							"secureInput": false
						},
						"userProperties": [],
						"typeProperties": {
							"dataset": {
								"referenceName": "blob_folder_name",
								"type": "DatasetReference",
								"parameters": {
									"foldername": "Input"
								}
							},
							"fieldList": [
								"lastModified",
								"itemType",
								"itemName",
								"exists",
								"childItems"
							],
							"storeSettings": {
								"type": "AzureBlobFSReadSettings",
								"recursive": true,
								"enablePartitionDiscovery": false
							},
							"formatSettings": {
								"type": "DelimitedTextReadSettings"
							}
						}
					},
					{
						"name": "Get Metadata_DATABASE",
						"type": "GetMetadata",
						"dependsOn": [],
						"policy": {
							"timeout": "0.12:00:00",
							"retry": 0,
							"retryIntervalInSeconds": 30,
							"secureOutput": false,
							"secureInput": false
						},
						"userProperties": [],
						"typeProperties": {
							"dataset": {
								"referenceName": "Dynamic_sql_table",
								"type": "DatasetReference",
								"parameters": {
									"tablename": "TABLEB"
								}
							},
							"fieldList": [
								"structure",
								"exists",
								"columnCount"
							]
						}
					}
				],
				"policy": {
					"elapsedTimeMetric": {}
				},
				"annotations": [],
				"lastPublishTime": "2024-11-19T03:31:37Z"
			},
			"dependsOn": []
		},
		{
			"name": "[concat(parameters('factoryName'), '/Get_copy_list')]",
			"type": "Microsoft.DataFactory/factories/pipelines",
			"apiVersion": "2018-06-01",
			"properties": {
				"activities": [
					{
						"name": "Lookup1",
						"type": "Lookup",
						"dependsOn": [],
						"policy": {
							"timeout": "0.12:00:00",
							"retry": 0,
							"retryIntervalInSeconds": 30,
							"secureOutput": false,
							"secureInput": false
						},
						"userProperties": [],
						"typeProperties": {
							"source": {
								"type": "AzureSqlSource",
								"queryTimeout": "02:00:00",
								"partitionOption": "None"
							},
							"dataset": {
								"referenceName": "Dynamic_sql_table",
								"type": "DatasetReference",
								"parameters": {
									"tablename": "DAILY_COPY_LIST"
								}
							},
							"firstRowOnly": false
						}
					},
					{
						"name": "ForEach1",
						"type": "ForEach",
						"dependsOn": [
							{
								"activity": "Lookup1",
								"dependencyConditions": [
									"Succeeded"
								]
							}
						],
						"userProperties": [],
						"typeProperties": {
							"items": {
								"value": "@activity('Lookup1').output.value",
								"type": "Expression"
							},
							"activities": [
								{
									"name": "Copy data1",
									"type": "Copy",
									"dependsOn": [],
									"policy": {
										"timeout": "0.12:00:00",
										"retry": 0,
										"retryIntervalInSeconds": 30,
										"secureOutput": false,
										"secureInput": false
									},
									"userProperties": [],
									"typeProperties": {
										"source": {
											"type": "AzureSqlSource",
											"queryTimeout": "02:00:00",
											"partitionOption": "None"
										},
										"sink": {
											"type": "AzureSqlSink",
											"writeBehavior": "insert",
											"sqlWriterUseTableLock": false
										},
										"enableStaging": false,
										"translator": {
											"type": "TabularTranslator",
											"typeConversion": true,
											"typeConversionSettings": {
												"allowDataTruncation": true,
												"treatBooleanAsNumber": false
											}
										}
									},
									"inputs": [
										{
											"referenceName": "Dynamic_sql_table",
											"type": "DatasetReference",
											"parameters": {
												"tablename": {
													"value": "@item().INPUT_FILENAME",
													"type": "Expression"
												}
											}
										}
									],
									"outputs": [
										{
											"referenceName": "Dynamic_sql_table",
											"type": "DatasetReference",
											"parameters": {
												"tablename": {
													"value": "@item().OUTPUT_FILENAME",
													"type": "Expression"
												}
											}
										}
									]
								}
							]
						}
					}
				],
				"policy": {
					"elapsedTimeMetric": {}
				},
				"annotations": [],
				"lastPublishTime": "2024-11-19T03:31:37Z"
			},
			"dependsOn": []
		},
		{
			"name": "[concat(parameters('factoryName'), '/IF_ACTIVITY')]",
			"type": "Microsoft.DataFactory/factories/pipelines",
			"apiVersion": "2018-06-01",
			"properties": {
				"activities": [
					{
						"name": "If Condition1",
						"type": "IfCondition",
						"dependsOn": [
							{
								"activity": "Get Metadata1",
								"dependencyConditions": [
									"Succeeded"
								]
							}
						],
						"userProperties": [],
						"typeProperties": {
							"expression": {
								"value": "@activity('Get Metadata1').output.exists",
								"type": "Expression"
							},
							"ifFalseActivities": [
								{
									"name": "False_Wait",
									"type": "Wait",
									"dependsOn": [],
									"userProperties": [],
									"typeProperties": {
										"waitTimeInSeconds": 1
									}
								}
							],
							"ifTrueActivities": [
								{
									"name": "True_Wait",
									"type": "Wait",
									"dependsOn": [],
									"userProperties": [],
									"typeProperties": {
										"waitTimeInSeconds": 1
									}
								}
							]
						}
					},
					{
						"name": "Get Metadata1",
						"type": "GetMetadata",
						"dependsOn": [],
						"policy": {
							"timeout": "0.12:00:00",
							"retry": 0,
							"retryIntervalInSeconds": 30,
							"secureOutput": false,
							"secureInput": false
						},
						"userProperties": [],
						"typeProperties": {
							"dataset": {
								"referenceName": "blob_file_param",
								"type": "DatasetReference",
								"parameters": {
									"filename": "emp_sal.csv"
								}
							},
							"fieldList": [
								"exists"
							],
							"storeSettings": {
								"type": "AzureBlobFSReadSettings",
								"recursive": true,
								"enablePartitionDiscovery": false
							},
							"formatSettings": {
								"type": "DelimitedTextReadSettings"
							}
						}
					}
				],
				"policy": {
					"elapsedTimeMetric": {}
				},
				"annotations": [],
				"lastPublishTime": "2024-11-20T03:11:55Z"
			},
			"dependsOn": []
		},
		{
			"name": "[concat(parameters('factoryName'), '/IF_ACTIVITY_2')]",
			"type": "Microsoft.DataFactory/factories/pipelines",
			"apiVersion": "2018-06-01",
			"properties": {
				"activities": [
					{
						"name": "Input_lookup",
						"type": "Lookup",
						"dependsOn": [],
						"policy": {
							"timeout": "0.12:00:00",
							"retry": 0,
							"retryIntervalInSeconds": 30,
							"secureOutput": false,
							"secureInput": false
						},
						"userProperties": [],
						"typeProperties": {
							"source": {
								"type": "AzureSqlSource",
								"sqlReaderQuery": "SELECT MAX(TrxnDate) as Input_Table_Date from DBO.IfTable_input",
								"queryTimeout": "02:00:00",
								"partitionOption": "None"
							},
							"dataset": {
								"referenceName": "Dynamic_sql_table",
								"type": "DatasetReference",
								"parameters": {
									"tablename": "IfTable_Input"
								}
							}
						}
					},
					{
						"name": "Output_Lookup",
						"type": "Lookup",
						"dependsOn": [],
						"policy": {
							"timeout": "0.12:00:00",
							"retry": 0,
							"retryIntervalInSeconds": 30,
							"secureOutput": false,
							"secureInput": false
						},
						"userProperties": [],
						"typeProperties": {
							"source": {
								"type": "AzureSqlSource",
								"sqlReaderQuery": "SELECT MAX(TrxnDate) as Output_Table_Date from DBO.IfTable_output",
								"queryTimeout": "02:00:00",
								"partitionOption": "None"
							},
							"dataset": {
								"referenceName": "Dynamic_sql_table",
								"type": "DatasetReference",
								"parameters": {
									"tablename": ".IfTable_output"
								}
							}
						}
					},
					{
						"name": "If Condition1",
						"type": "IfCondition",
						"dependsOn": [
							{
								"activity": "Input_lookup",
								"dependencyConditions": [
									"Succeeded"
								]
							},
							{
								"activity": "Output_Lookup",
								"dependencyConditions": [
									"Succeeded"
								]
							}
						],
						"userProperties": [],
						"typeProperties": {
							"expression": {
								"value": "@greater(\r\n    activity('Input_lookup').output.firstRow.Input_Table_Date,\r\n    activity('Output_Lookup').output.firstRow.Output_Table_Date\r\n)",
								"type": "Expression"
							},
							"ifFalseActivities": [
								{
									"name": "Fail1",
									"type": "Fail",
									"dependsOn": [],
									"userProperties": [],
									"typeProperties": {
										"message": "Input_Table_Data is not latest",
										"errorCode": "403"
									}
								}
							],
							"ifTrueActivities": [
								{
									"name": "Copy data_True",
									"type": "Copy",
									"dependsOn": [],
									"policy": {
										"timeout": "0.12:00:00",
										"retry": 0,
										"retryIntervalInSeconds": 30,
										"secureOutput": false,
										"secureInput": false
									},
									"userProperties": [],
									"typeProperties": {
										"source": {
											"type": "AzureSqlSource",
											"queryTimeout": "02:00:00",
											"partitionOption": "None"
										},
										"sink": {
											"type": "AzureSqlSink",
											"writeBehavior": "insert",
											"sqlWriterUseTableLock": false
										},
										"enableStaging": false,
										"translator": {
											"type": "TabularTranslator",
											"typeConversion": true,
											"typeConversionSettings": {
												"allowDataTruncation": true,
												"treatBooleanAsNumber": false
											}
										}
									},
									"inputs": [
										{
											"referenceName": "Dynamic_sql_table",
											"type": "DatasetReference",
											"parameters": {
												"tablename": "IfTable_input"
											}
										}
									],
									"outputs": [
										{
											"referenceName": "Dynamic_sql_table",
											"type": "DatasetReference",
											"parameters": {
												"tablename": "IfTable_Output"
											}
										}
									]
								}
							]
						}
					}
				],
				"policy": {
					"elapsedTimeMetric": {}
				},
				"annotations": [],
				"lastPublishTime": "2024-11-20T03:11:55Z"
			},
			"dependsOn": []
		},
		{
			"name": "[concat(parameters('factoryName'), '/Multi_Copy')]",
			"type": "Microsoft.DataFactory/factories/pipelines",
			"apiVersion": "2018-06-01",
			"properties": {
				"activities": [
					{
						"name": "Copy data1",
						"type": "Copy",
						"dependsOn": [],
						"policy": {
							"timeout": "0.12:00:00",
							"retry": 0,
							"retryIntervalInSeconds": 30,
							"secureOutput": false,
							"secureInput": false
						},
						"userProperties": [],
						"typeProperties": {
							"source": {
								"type": "DelimitedTextSource",
								"storeSettings": {
									"type": "AzureBlobFSReadSettings",
									"recursive": true,
									"wildcardFolderPath": "Input",
									"wildcardFileName": "Cus*.csv",
									"enablePartitionDiscovery": false
								},
								"formatSettings": {
									"type": "DelimitedTextReadSettings"
								}
							},
							"sink": {
								"type": "DelimitedTextSink",
								"storeSettings": {
									"type": "AzureBlobFSWriteSettings",
									"copyBehavior": "MergeFiles"
								},
								"formatSettings": {
									"type": "DelimitedTextWriteSettings",
									"quoteAllText": true,
									"fileExtension": ".txt"
								}
							},
							"enableStaging": false,
							"translator": {
								"type": "TabularTranslator",
								"typeConversion": true,
								"typeConversionSettings": {
									"allowDataTruncation": true,
									"treatBooleanAsNumber": false
								}
							}
						},
						"inputs": [
							{
								"referenceName": "blob_folder_name",
								"type": "DatasetReference",
								"parameters": {
									"foldername": "Input"
								}
							}
						],
						"outputs": [
							{
								"referenceName": "blob_folder_name",
								"type": "DatasetReference",
								"parameters": {
									"foldername": "Output"
								}
							}
						]
					}
				],
				"policy": {
					"elapsedTimeMetric": {}
				},
				"annotations": [],
				"lastPublishTime": "2024-11-15T03:27:08Z"
			},
			"dependsOn": []
		},
		{
			"name": "[concat(parameters('factoryName'), '/ONPREM_2_BRONZE')]",
			"type": "Microsoft.DataFactory/factories/pipelines",
			"apiVersion": "2018-06-01",
			"properties": {
				"activities": [
					{
						"name": "Copy data1",
						"type": "Copy",
						"dependsOn": [],
						"policy": {
							"timeout": "0.12:00:00",
							"retry": 0,
							"retryIntervalInSeconds": 30,
							"secureOutput": false,
							"secureInput": false
						},
						"userProperties": [],
						"typeProperties": {
							"source": {
								"type": "AzureSqlSource",
								"queryTimeout": "02:00:00",
								"partitionOption": "None"
							},
							"sink": {
								"type": "ParquetSink",
								"storeSettings": {
									"type": "AzureBlobFSWriteSettings"
								},
								"formatSettings": {
									"type": "ParquetWriteSettings"
								}
							},
							"enableStaging": false,
							"translator": {
								"type": "TabularTranslator",
								"typeConversion": true,
								"typeConversionSettings": {
									"allowDataTruncation": true,
									"treatBooleanAsNumber": false
								}
							}
						},
						"inputs": [
							{
								"referenceName": "Dynamic_sql_table",
								"type": "DatasetReference",
								"parameters": {
									"tablename": {
										"value": "@pipeline().parameters.Table_Name",
										"type": "Expression"
									}
								}
							}
						],
						"outputs": [
							{
								"referenceName": "bronze_parquet",
								"type": "DatasetReference",
								"parameters": {
									"folder_Name": {
										"value": "@pipeline().parameters.Table_Name",
										"type": "Expression"
									},
									"File_Name": {
										"value": "@concat(pipeline().parameters.Table_Name,'.parquet')",
										"type": "Expression"
									}
								}
							}
						]
					}
				],
				"policy": {
					"elapsedTimeMetric": {}
				},
				"parameters": {
					"Table_Name": {
						"type": "string"
					}
				},
				"annotations": [],
				"lastPublishTime": "2024-11-25T04:56:16Z"
			},
			"dependsOn": []
		},
		{
			"name": "[concat(parameters('factoryName'), '/PIPELINE_LOGICAPP_TEST')]",
			"type": "Microsoft.DataFactory/factories/pipelines",
			"apiVersion": "2018-06-01",
			"properties": {
				"activities": [
					{
						"name": "Get Metadata1",
						"type": "GetMetadata",
						"dependsOn": [],
						"policy": {
							"timeout": "0.12:00:00",
							"retry": 0,
							"retryIntervalInSeconds": 30,
							"secureOutput": false,
							"secureInput": false
						},
						"userProperties": [],
						"typeProperties": {
							"dataset": {
								"referenceName": "blob_file_param",
								"type": "DatasetReference",
								"parameters": {
									"filename": {
										"value": "@pipeline().parameters.FileName",
										"type": "Expression"
									}
								}
							},
							"fieldList": [
								"exists"
							],
							"storeSettings": {
								"type": "AzureBlobFSReadSettings",
								"recursive": true,
								"enablePartitionDiscovery": false
							},
							"formatSettings": {
								"type": "DelimitedTextReadSettings"
							}
						}
					},
					{
						"name": "If Condition1",
						"type": "IfCondition",
						"dependsOn": [
							{
								"activity": "Get Metadata1",
								"dependencyConditions": [
									"Succeeded"
								]
							}
						],
						"userProperties": [],
						"typeProperties": {
							"expression": {
								"value": "@activity('Get Metadata1').output.exists",
								"type": "Expression"
							},
							"ifFalseActivities": [
								{
									"name": "Web1",
									"type": "WebActivity",
									"dependsOn": [],
									"policy": {
										"timeout": "0.12:00:00",
										"retry": 0,
										"retryIntervalInSeconds": 30,
										"secureOutput": false,
										"secureInput": false
									},
									"userProperties": [],
									"typeProperties": {
										"method": "POST",
										"headers": {
											"Content-Type": "application/json"
										},
										"url": "https://prod-01.centralindia.logic.azure.com:443/workflows/7be5b63a34d64db3828caaec7916d849/triggers/When_a_HTTP_request_is_received/paths/invoke?api-version=2016-10-01&sp=%2Ftriggers%2FWhen_a_HTTP_request_is_received%2Frun&sv=1.0&sig=XLlQfhnYl6Q4BqL_KXWSq6ghO8va5ylA9J2gZ7U3_Rs",
										"body": {
											"value": "{\n    \"PipelineName\": \"@{pipeline().Pipeline}\",\n    \"DataFactoryName\": \"@{pipeline().DataFactory}\",\n    \"ErrorMessage\": \"404-FILE NOT FOUND\"\n}",
											"type": "Expression"
										}
									}
								},
								{
									"name": "Fail1",
									"type": "Fail",
									"dependsOn": [
										{
											"activity": "Web1",
											"dependencyConditions": [
												"Succeeded"
											]
										}
									],
									"userProperties": [],
									"typeProperties": {
										"message": "FILE NOT FOUND",
										"errorCode": "404"
									}
								}
							],
							"ifTrueActivities": [
								{
									"name": "Copy data1",
									"type": "Copy",
									"dependsOn": [],
									"policy": {
										"timeout": "0.12:00:00",
										"retry": 0,
										"retryIntervalInSeconds": 30,
										"secureOutput": false,
										"secureInput": false
									},
									"userProperties": [],
									"typeProperties": {
										"source": {
											"type": "DelimitedTextSource",
											"storeSettings": {
												"type": "AzureBlobFSReadSettings",
												"recursive": true,
												"enablePartitionDiscovery": false
											},
											"formatSettings": {
												"type": "DelimitedTextReadSettings"
											}
										},
										"sink": {
											"type": "DelimitedTextSink",
											"storeSettings": {
												"type": "AzureBlobFSWriteSettings"
											},
											"formatSettings": {
												"type": "DelimitedTextWriteSettings",
												"quoteAllText": true,
												"fileExtension": ".txt"
											}
										},
										"enableStaging": false,
										"translator": {
											"type": "TabularTranslator",
											"typeConversion": true,
											"typeConversionSettings": {
												"allowDataTruncation": true,
												"treatBooleanAsNumber": false
											}
										}
									},
									"inputs": [
										{
											"referenceName": "blob_file_param",
											"type": "DatasetReference",
											"parameters": {
												"filename": {
													"value": "@pipeline().parameters.FileName",
													"type": "Expression"
												}
											}
										}
									],
									"outputs": [
										{
											"referenceName": "blob_folder_name",
											"type": "DatasetReference",
											"parameters": {
												"foldername": "Output"
											}
										}
									]
								}
							]
						}
					}
				],
				"policy": {
					"elapsedTimeMetric": {}
				},
				"parameters": {
					"FileName": {
						"type": "string"
					}
				},
				"annotations": [],
				"lastPublishTime": "2024-11-25T04:56:16Z"
			},
			"dependsOn": []
		},
		{
			"name": "[concat(parameters('factoryName'), '/SILVER_2_GOLD')]",
			"type": "Microsoft.DataFactory/factories/pipelines",
			"apiVersion": "2018-06-01",
			"properties": {
				"activities": [
					{
						"name": "Notebook1",
						"type": "DatabricksNotebook",
						"dependsOn": [],
						"policy": {
							"timeout": "0.12:00:00",
							"retry": 0,
							"retryIntervalInSeconds": 30,
							"secureOutput": false,
							"secureInput": false
						},
						"userProperties": [],
						"typeProperties": {
							"notebookPath": "/Users/bollachanti@gmail.com/SILVER_2_GOLD"
						},
						"linkedServiceName": {
							"referenceName": "LS_DBS",
							"type": "LinkedServiceReference"
						}
					}
				],
				"policy": {
					"elapsedTimeMetric": {}
				},
				"annotations": [],
				"lastPublishTime": "2024-11-25T05:21:23Z"
			},
			"dependsOn": [
				"[concat(variables('factoryId'), '/linkedServices/LS_DBS')]"
			]
		},
		{
			"name": "[concat(parameters('factoryName'), '/SQL2_SQL')]",
			"type": "Microsoft.DataFactory/factories/pipelines",
			"apiVersion": "2018-06-01",
			"properties": {
				"activities": [
					{
						"name": "Copy data1",
						"type": "Copy",
						"dependsOn": [],
						"policy": {
							"timeout": "0.12:00:00",
							"retry": 0,
							"retryIntervalInSeconds": 30,
							"secureOutput": false,
							"secureInput": false
						},
						"userProperties": [],
						"typeProperties": {
							"source": {
								"type": "AzureSqlSource",
								"sqlReaderQuery": "SELECT ID, NAME FROM DBO.TABLEB",
								"queryTimeout": "02:00:00",
								"partitionOption": "None"
							},
							"sink": {
								"type": "AzureSqlSink",
								"writeBehavior": "insert",
								"sqlWriterUseTableLock": false
							},
							"enableStaging": false,
							"translator": {
								"type": "TabularTranslator",
								"typeConversion": true,
								"typeConversionSettings": {
									"allowDataTruncation": true,
									"treatBooleanAsNumber": false
								}
							}
						},
						"inputs": [
							{
								"referenceName": "Dynamic_sql_table",
								"type": "DatasetReference",
								"parameters": {
									"tablename": {
										"value": "@pipeline().parameters.InputTable",
										"type": "Expression"
									}
								}
							}
						],
						"outputs": [
							{
								"referenceName": "Dynamic_sql_table",
								"type": "DatasetReference",
								"parameters": {
									"tablename": {
										"value": "@pipeline().parameters.OutputTable",
										"type": "Expression"
									}
								}
							}
						]
					}
				],
				"policy": {
					"elapsedTimeMetric": {}
				},
				"parameters": {
					"InputTable": {
						"type": "String"
					},
					"OutputTable": {
						"type": "String"
					}
				},
				"annotations": [],
				"lastPublishTime": "2024-11-15T03:43:17Z"
			},
			"dependsOn": []
		},
		{
			"name": "[concat(parameters('factoryName'), '/SWITCH')]",
			"type": "Microsoft.DataFactory/factories/pipelines",
			"apiVersion": "2018-06-01",
			"properties": {
				"activities": [
					{
						"name": "ForEach1",
						"type": "ForEach",
						"dependsOn": [
							{
								"activity": "Lookup1",
								"dependencyConditions": [
									"Succeeded"
								]
							}
						],
						"userProperties": [],
						"typeProperties": {
							"items": {
								"value": "@activity('Lookup1').output.value",
								"type": "Expression"
							},
							"isSequential": true,
							"activities": [
								{
									"name": "Switch1",
									"type": "Switch",
									"dependsOn": [],
									"userProperties": [],
									"typeProperties": {
										"on": {
											"value": "@item().COUNTRY",
											"type": "Expression"
										},
										"cases": [
											{
												"value": "INDIA",
												"activities": [
													{
														"name": "Copy data_INDIA",
														"type": "Copy",
														"dependsOn": [],
														"policy": {
															"timeout": "0.12:00:00",
															"retry": 0,
															"retryIntervalInSeconds": 30,
															"secureOutput": false,
															"secureInput": false
														},
														"userProperties": [],
														"typeProperties": {
															"source": {
																"type": "AzureSqlSource",
																"sqlReaderQuery": "SELECT NAME, ADDRESS, CITY, COUNTRY FROM DBO.ADDRESS_COMMON\nWHERE COUNTRY = 'INDIA'",
																"queryTimeout": "02:00:00",
																"partitionOption": "None"
															},
															"sink": {
																"type": "AzureSqlSink",
																"writeBehavior": "insert",
																"sqlWriterUseTableLock": false
															},
															"enableStaging": false,
															"translator": {
																"type": "TabularTranslator",
																"typeConversion": true,
																"typeConversionSettings": {
																	"allowDataTruncation": true,
																	"treatBooleanAsNumber": false
																}
															}
														},
														"inputs": [
															{
																"referenceName": "Dynamic_sql_table",
																"type": "DatasetReference",
																"parameters": {
																	"tablename": "ADDRESS_COMMON"
																}
															}
														],
														"outputs": [
															{
																"referenceName": "Dynamic_sql_table",
																"type": "DatasetReference",
																"parameters": {
																	"tablename": "ADDRESS_INDIA"
																}
															}
														]
													}
												]
											},
											{
												"value": "USA",
												"activities": [
													{
														"name": "Copy data_USA",
														"type": "Copy",
														"dependsOn": [],
														"policy": {
															"timeout": "0.12:00:00",
															"retry": 0,
															"retryIntervalInSeconds": 30,
															"secureOutput": false,
															"secureInput": false
														},
														"userProperties": [],
														"typeProperties": {
															"source": {
																"type": "AzureSqlSource",
																"sqlReaderQuery": "SELECT * FROM DBO.ADDRESS_COMMON\nWHERE COUNTRY = 'USA'",
																"queryTimeout": "02:00:00",
																"partitionOption": "None"
															},
															"sink": {
																"type": "AzureSqlSink",
																"writeBehavior": "insert",
																"sqlWriterUseTableLock": false
															},
															"enableStaging": false,
															"translator": {
																"type": "TabularTranslator",
																"typeConversion": true,
																"typeConversionSettings": {
																	"allowDataTruncation": true,
																	"treatBooleanAsNumber": false
																}
															}
														},
														"inputs": [
															{
																"referenceName": "Dynamic_sql_table",
																"type": "DatasetReference",
																"parameters": {
																	"tablename": "ADDRESS_COMMON"
																}
															}
														],
														"outputs": [
															{
																"referenceName": "Dynamic_sql_table",
																"type": "DatasetReference",
																"parameters": {
																	"tablename": "ADDRESS_USA"
																}
															}
														]
													}
												]
											}
										],
										"defaultActivities": [
											{
												"name": "Copy data_OTHERS",
												"type": "Copy",
												"dependsOn": [],
												"policy": {
													"timeout": "0.12:00:00",
													"retry": 0,
													"retryIntervalInSeconds": 30,
													"secureOutput": false,
													"secureInput": false
												},
												"userProperties": [],
												"typeProperties": {
													"source": {
														"type": "AzureSqlSource",
														"sqlReaderQuery": "SELECT * FROM DBO.ADDRESS_COMMON\nWHERE COUNTRY NOT IN ('INDIA','USA')",
														"queryTimeout": "02:00:00",
														"partitionOption": "None"
													},
													"sink": {
														"type": "AzureSqlSink",
														"writeBehavior": "insert",
														"sqlWriterUseTableLock": false
													},
													"enableStaging": false,
													"translator": {
														"type": "TabularTranslator",
														"typeConversion": true,
														"typeConversionSettings": {
															"allowDataTruncation": true,
															"treatBooleanAsNumber": false
														}
													}
												},
												"inputs": [
													{
														"referenceName": "Dynamic_sql_table",
														"type": "DatasetReference",
														"parameters": {
															"tablename": "ADDRESS_COMMON"
														}
													}
												],
												"outputs": [
													{
														"referenceName": "Dynamic_sql_table",
														"type": "DatasetReference",
														"parameters": {
															"tablename": "ADDRESS_OTHERS"
														}
													}
												]
											}
										]
									}
								}
							]
						}
					},
					{
						"name": "Lookup1",
						"type": "Lookup",
						"dependsOn": [],
						"policy": {
							"timeout": "0.12:00:00",
							"retry": 0,
							"retryIntervalInSeconds": 30,
							"secureOutput": false,
							"secureInput": false
						},
						"userProperties": [],
						"typeProperties": {
							"source": {
								"type": "AzureSqlSource",
								"sqlReaderQuery": "SELECT DISTINCT COUNTRY FROM DBO.ADDRESS_COMMON",
								"queryTimeout": "02:00:00",
								"partitionOption": "None"
							},
							"dataset": {
								"referenceName": "Dynamic_sql_table",
								"type": "DatasetReference",
								"parameters": {
									"tablename": "ADDRESS_COMMON"
								}
							},
							"firstRowOnly": false
						}
					}
				],
				"policy": {
					"elapsedTimeMetric": {}
				},
				"variables": {
					"Index_Val": {
						"type": "String"
					}
				},
				"annotations": [],
				"lastPublishTime": "2024-11-21T03:56:00Z"
			},
			"dependsOn": []
		},
		{
			"name": "[concat(parameters('factoryName'), '/Tumbling_TRIGGER_PIPELINE')]",
			"type": "Microsoft.DataFactory/factories/pipelines",
			"apiVersion": "2018-06-01",
			"properties": {
				"activities": [
					{
						"name": "Copy data1",
						"type": "Copy",
						"dependsOn": [],
						"policy": {
							"timeout": "0.12:00:00",
							"retry": 0,
							"retryIntervalInSeconds": 30,
							"secureOutput": false,
							"secureInput": false
						},
						"userProperties": [],
						"typeProperties": {
							"source": {
								"type": "AzureSqlSource",
								"sqlReaderStoredProcedureName": "[[dbo].[TUMBLING_WINDOW_PROC]",
								"storedProcedureParameters": {
									"ENDDATE": {
										"type": "String",
										"value": {
											"value": "@pipeline().parameters.windowEndTime",
											"type": "Expression"
										}
									},
									"STARTDATE": {
										"type": "String",
										"value": {
											"value": "@pipeline().parameters.windowStartTime",
											"type": "Expression"
										}
									}
								},
								"queryTimeout": "02:00:00",
								"partitionOption": "None"
							},
							"sink": {
								"type": "AzureSqlSink",
								"writeBehavior": "insert",
								"sqlWriterUseTableLock": false
							},
							"enableStaging": false,
							"translator": {
								"type": "TabularTranslator",
								"typeConversion": true,
								"typeConversionSettings": {
									"allowDataTruncation": true,
									"treatBooleanAsNumber": false
								}
							}
						},
						"inputs": [
							{
								"referenceName": "Dynamic_sql_table",
								"type": "DatasetReference",
								"parameters": {
									"tablename": "CUST_SOURCE"
								}
							}
						],
						"outputs": [
							{
								"referenceName": "Dynamic_sql_table",
								"type": "DatasetReference",
								"parameters": {
									"tablename": "Tumbling_Cust"
								}
							}
						]
					}
				],
				"policy": {
					"elapsedTimeMetric": {}
				},
				"parameters": {
					"windowStartTime": {
						"type": "string"
					},
					"windowEndTime": {
						"type": "string"
					}
				},
				"annotations": [],
				"lastPublishTime": "2024-11-23T03:52:32Z"
			},
			"dependsOn": []
		},
		{
			"name": "[concat(parameters('factoryName'), '/eventbased_PIPELINE')]",
			"type": "Microsoft.DataFactory/factories/pipelines",
			"apiVersion": "2018-06-01",
			"properties": {
				"activities": [
					{
						"name": "Copy data1",
						"type": "Copy",
						"dependsOn": [],
						"policy": {
							"timeout": "0.12:00:00",
							"retry": 0,
							"retryIntervalInSeconds": 30,
							"secureOutput": false,
							"secureInput": false
						},
						"userProperties": [],
						"typeProperties": {
							"source": {
								"type": "DelimitedTextSource",
								"storeSettings": {
									"type": "AzureBlobFSReadSettings",
									"recursive": true,
									"wildcardFolderPath": "Input",
									"wildcardFileName": "*",
									"enablePartitionDiscovery": false
								},
								"formatSettings": {
									"type": "DelimitedTextReadSettings"
								}
							},
							"sink": {
								"type": "DelimitedTextSink",
								"storeSettings": {
									"type": "AzureBlobFSWriteSettings"
								},
								"formatSettings": {
									"type": "DelimitedTextWriteSettings",
									"quoteAllText": true,
									"fileExtension": ".txt"
								}
							},
							"enableStaging": false,
							"translator": {
								"type": "TabularTranslator",
								"typeConversion": true,
								"typeConversionSettings": {
									"allowDataTruncation": true,
									"treatBooleanAsNumber": false
								}
							}
						},
						"inputs": [
							{
								"referenceName": "EventbasedInput",
								"type": "DatasetReference",
								"parameters": {}
							}
						],
						"outputs": [
							{
								"referenceName": "eventbasedoutput",
								"type": "DatasetReference",
								"parameters": {}
							}
						]
					},
					{
						"name": "Delete1",
						"type": "Delete",
						"dependsOn": [
							{
								"activity": "Copy data1",
								"dependencyConditions": [
									"Succeeded"
								]
							}
						],
						"policy": {
							"timeout": "0.12:00:00",
							"retry": 0,
							"retryIntervalInSeconds": 30,
							"secureOutput": false,
							"secureInput": false
						},
						"userProperties": [],
						"typeProperties": {
							"dataset": {
								"referenceName": "EventbasedInput",
								"type": "DatasetReference",
								"parameters": {}
							},
							"enableLogging": false,
							"storeSettings": {
								"type": "AzureBlobFSReadSettings",
								"recursive": true,
								"wildcardFileName": "*",
								"enablePartitionDiscovery": false
							}
						}
					}
				],
				"policy": {
					"elapsedTimeMetric": {}
				},
				"annotations": [],
				"lastPublishTime": "2024-11-23T03:35:17Z"
			},
			"dependsOn": []
		}
	]
}